{ "databaseChangeLog": [
    {
        "changeSet": {
          "id": "UCSBOrganizations",
          "author": "pgunhal",
          "preConditions": [
            {
              "onFail": "MARK_RAN"
            },
            {
              "not": [
                {
                  "tableExists": {
                    "tableName": "UCSBORGANIZATIONS"
                  }
                }
              ]
            }
          ],
          "changes": [
            {
              "createTable": {
                "columns": [
                  {
                    "column": {
                      "constraints": {
                        "primaryKey": true,
                        "primaryKeyName": "ORGANIZATIONS_PK"
                      },
                      "name": "ORGCODE",
                      "type": "VARCHAR(255)"
                    }
                  },
                  {
                    "column": {
                      "name": "ORGTRANSLATIONSHORT",
                      "type": "VARCHAR(255)"
                    }
                  },
                   {
                    "column": {
                      "name": "ORGTRANSLATION",
                      "type": "VARCHAR(255)"
                    }
                  },
                  {
                    "column": {
                      "constraints": {
                        "nullable": false
                      },
                      "name": "INACTIVE",
                      "type": "BOOLEAN"
                    }
                  }
                ],
                "tableName": "UCSBORGANIZATIONS"
              }
            }]

        }
    }
]}
